k3im/__init__.py
k3im/cait.py
k3im/cait_1d.py
k3im/cait_3d.py
k3im/cct.py
k3im/cct_1d.py
k3im/cct_3d.py
k3im/convmixer.py
k3im/convmixer_1d.py
k3im/convmixer_3d.py
k3im/cross_vit.py
k3im/deepvit.py
k3im/eanet.py
k3im/eanet3d.py
k3im/eanet_1d.py
k3im/fnet.py
k3im/fnet_1d.py
k3im/fnet_3d.py
k3im/focalnet.py
k3im/gmlp.py
k3im/gmlp_1d.py
k3im/gmlp_3d.py
k3im/mlp_mixer.py
k3im/mlp_mixer_1d.py
k3im/mlp_mixer_3d.py
k3im/simple_vit.py
k3im/simple_vit_1d.py
k3im/simple_vit_3d.py
k3im/simple_vit_with_fft.py
k3im/simple_vit_with_register_tokens.py
k3im/swint.py
k3im/token_learner.py
k3im/video_eanet.py
k3im/video_mixer.py
k3im/vit.py
k3im/vit_1d.py
k3im/vit_3d.py
k3im/vit_with_patch_dropout.py
k3im/vivit.py
k3im-0.0.11.dist-info/LICENSE
k3im-0.0.11.dist-info/METADATA
k3im-0.0.11.dist-info/WHEEL
k3im-0.0.11.dist-info/RECORD
