Metadata-Version: 2.1
Name: k3im
Version: 0.0.11
Summary: 
License: MIT
Author: Muhammad Anas Raza
Author-email: memanasraza@gmail.com
Requires-Python: >=3.10,<4.0
Classifier: License :: OSI Approved :: MIT License
Classifier: Programming Language :: Python :: 3
Classifier: Programming Language :: Python :: 3.10
Classifier: Programming Language :: Python :: 3.11
Classifier: Programming Language :: Python :: 3.12
Requires-Dist: keras (>=3.0.0)
